yaxil/__init__.py
yaxil/__version__.py
yaxil/assessments/__init__.py
yaxil/assessments/neuroinfo/__init__.py
yaxil/assessments/neuroinfo/legacy/__init__.py
yaxil/assessments/neuroinfo/session/__init__.py
yaxil/bids/__init__.py
yaxil/commons/__init__.py
yaxil/dicom/__init__.py
yaxil/exceptions/__init__.py
yaxil/functools/__init__.py
yaxil/session/__init__.py
yaxil-0.13.1.data/scripts/ArcGet.py
yaxil-0.13.1.data/scripts/xnat_auth
yaxil-0.13.1.dist-info/licenses/LICENSE
yaxil-0.13.1.dist-info/METADATA
yaxil-0.13.1.dist-info/WHEEL
yaxil-0.13.1.dist-info/top_level.txt
yaxil-0.13.1.dist-info/RECORD
