Metadata-Version: 2.4
Name: yaxil
Version: 0.13.1
Summary: Yet another XNAT interface libary
Home-page: https://github.com/harvard-nrg/yaxil
Author: Neuroinformatics Research Group
Author-email: info@neuroinfo.org
License-File: LICENSE
Requires-Dist: requests
Requires-Dist: pydicom
Requires-Dist: nibabel
Requires-Dist: natsort
Requires-Dist: arrow
Requires-Dist: pyaml
Requires-Dist: lxml
Requires-Dist: six
Requires-Dist: jsonpath-ng
Dynamic: author
Dynamic: author-email
Dynamic: home-page
Dynamic: license-file
Dynamic: requires-dist
Dynamic: summary
